{"uuid":"96fa3651-961f-4645-8a10-16837e6c2b4b","nbt":{"Tags":["\"Door\"","\"96fa3651-961f-4645-8a10-16837e6c2b4b\"","\"FromServer\"","\"Displays\"","\"BlockDisplays\""],"Pos":["10d","-60d","0d"],"CustomName":"\"\\\"96fa3651-961f-4645-8a10-16837e6c2b4b\\\"\"","CustomNameVisible":"0","block_state":"{Name:\"minecraft:spruce_door\",Properties:{facing:\"south\",half:\"lower\",hinge:\"right\",open:\"false\"}}","transformation":"{translation:[1f,0f,1f],left_rotation:[0f,0f,0f,1f],scale:[1f,1f,1f],right_rotation:[0f,1f,0f,0f]}"}}